endex_factset_mergers_and_acquisitions/__init__.py
endex_factset_mergers_and_acquisitions/_base_client.py
endex_factset_mergers_and_acquisitions/_client.py
endex_factset_mergers_and_acquisitions/_compat.py
endex_factset_mergers_and_acquisitions/_constants.py
endex_factset_mergers_and_acquisitions/_exceptions.py
endex_factset_mergers_and_acquisitions/_files.py
endex_factset_mergers_and_acquisitions/_models.py
endex_factset_mergers_and_acquisitions/_qs.py
endex_factset_mergers_and_acquisitions/_resource.py
endex_factset_mergers_and_acquisitions/_response.py
endex_factset_mergers_and_acquisitions/_streaming.py
endex_factset_mergers_and_acquisitions/_types.py
endex_factset_mergers_and_acquisitions/_version.py
endex_factset_mergers_and_acquisitions/py.typed
endex_factset_mergers_and_acquisitions/_utils/__init__.py
endex_factset_mergers_and_acquisitions/_utils/_logs.py
endex_factset_mergers_and_acquisitions/_utils/_proxy.py
endex_factset_mergers_and_acquisitions/_utils/_reflection.py
endex_factset_mergers_and_acquisitions/_utils/_streams.py
endex_factset_mergers_and_acquisitions/_utils/_sync.py
endex_factset_mergers_and_acquisitions/_utils/_transform.py
endex_factset_mergers_and_acquisitions/_utils/_typing.py
endex_factset_mergers_and_acquisitions/_utils/_utils.py
endex_factset_mergers_and_acquisitions/lib/.keep
endex_factset_mergers_and_acquisitions/resources/__init__.py
endex_factset_mergers_and_acquisitions/resources/deals.py
endex_factset_mergers_and_acquisitions/types/__init__.py
endex_factset_mergers_and_acquisitions/types/deal_by_company_params.py
endex_factset_mergers_and_acquisitions/types/deal_details_params.py
endex_factset_mergers_and_acquisitions/types/deal_public_targets_params.py
endex_factset_mergers_and_acquisitions/types/deals_public_response.py
endex_factset_mergers_and_acquisitions/types/deals_response.py
endex_factset_mergers_and_acquisitions/types/details_response.py
endex_factset_mergers_and_acquisitions-0.1.0a2.dist-info/METADATA
endex_factset_mergers_and_acquisitions-0.1.0a2.dist-info/WHEEL
endex_factset_mergers_and_acquisitions-0.1.0a2.dist-info/licenses/LICENSE
endex_factset_mergers_and_acquisitions-0.1.0a2.dist-info/RECORD
